{"etf_id":"0101N0","manager":"RISE","name":"RISE AI전력인프라","request_name":"RISE AI전력인프라","ticker":"0101N0","latest_date":"2026-07-22","prev_date":"2026-07-20","has_prev":true,"available_dates":["2026-07-22","2026-07-20","2026-07-17","2026-07-16","2026-07-15","2026-07-14","2026-07-13","2026-07-10","2026-07-09","2026-07-08","2026-07-07","2026-07-06","2026-07-03","2026-07-02"],"n_holdings":16,"rows":[{"stock_code":"000500","stock_name":"가온전선","weight":10.22,"weight_prev":11.85,"weight_delta":-1.63,"shares":492.0,"shares_prev":547.0,"shares_delta":-55.0,"amount":89101200.0,"amount_prev":107594900.0,"status":"same","is_cash":false,"share_changed":true},{"stock_code":"119850","stock_name":"지엔씨에너지","weight":7.71,"weight_prev":7.03,"weight_delta":0.68,"shares":1881.0,"shares_prev":1881.0,"shares_delta":0.0,"amount":67245750.0,"amount_prev":63859950.0,"status":"same","is_cash":false,"share_changed":false},{"stock_code":"267260","stock_name":"HD현대일렉트릭","weight":7.32,"weight_prev":7.64,"weight_delta":-0.32,"shares":82.0,"shares_prev":87.0,"shares_delta":-5.0,"amount":63796000.0,"amount_prev":69339000.0,"status":"same","is_cash":false,"share_changed":true},{"stock_code":"010120","stock_name":"LS ELECTRIC","weight":7.22,"weight_prev":7.53,"weight_delta":-0.31,"shares":333.0,"shares_prev":360.0,"shares_delta":-27.0,"amount":62970300.0,"amount_prev":68400000.0,"status":"same","is_cash":false,"share_changed":true},{"stock_code":"001440","stock_name":"대한전선","weight":6.98,"weight_prev":6.99,"weight_delta":-0.01,"shares":2290.0,"shares_prev":2290.0,"shares_delta":0.0,"amount":60799500.0,"amount_prev":63433000.0,"status":"same","is_cash":false,"share_changed":false},{"stock_code":"103590","stock_name":"일진전기","weight":6.67,"weight_prev":6.43,"weight_delta":0.24,"shares":981.0,"shares_prev":981.0,"shares_delta":0.0,"amount":58173300.0,"amount_prev":58369500.0,"status":"same","is_cash":false,"share_changed":false},{"stock_code":"373220","stock_name":"LG에너지솔루션","weight":6.55,"weight_prev":6.62,"weight_delta":-0.07,"shares":180.0,"shares_prev":180.0,"shares_delta":0.0,"amount":57060000.0,"amount_prev":60120000.0,"status":"same","is_cash":false,"share_changed":false},{"stock_code":"178320","stock_name":"서진시스템","weight":6.49,"weight_prev":6.76,"weight_delta":-0.27,"shares":1562.0,"shares_prev":1562.0,"shares_delta":0.0,"amount":56544400.0,"amount_prev":61386600.0,"status":"same","is_cash":false,"share_changed":false},{"stock_code":"229640","stock_name":"LS에코에너지","weight":6.27,"weight_prev":6.07,"weight_delta":0.2,"shares":1281.0,"shares_prev":1281.0,"shares_delta":0.0,"amount":54634650.0,"amount_prev":55147050.0,"status":"same","is_cash":false,"share_changed":false},{"stock_code":"033100","stock_name":"제룡전기","weight":6.19,"weight_prev":5.97,"weight_delta":0.22,"shares":1266.0,"shares_prev":1266.0,"shares_delta":0.0,"amount":53994900.0,"amount_prev":54184800.0,"status":"same","is_cash":false,"share_changed":false},{"stock_code":"298040","stock_name":"효성중공업","weight":5.62,"weight_prev":5.84,"weight_delta":-0.22,"shares":19.0,"shares_prev":19.0,"shares_delta":0.0,"amount":48982000.0,"amount_prev":52991000.0,"status":"same","is_cash":false,"share_changed":false},{"stock_code":"034020","stock_name":"두산에너빌리티","weight":5.59,"weight_prev":5.6,"weight_delta":-0.01,"shares":730.0,"shares_prev":730.0,"shares_delta":0.0,"amount":48764000.0,"amount_prev":50881000.0,"status":"same","is_cash":false,"share_changed":false},{"stock_code":"062040","stock_name":"산일전기","weight":5.58,"weight_prev":5.52,"weight_delta":0.06,"shares":295.0,"shares_prev":295.0,"shares_delta":0.0,"amount":48616000.0,"amount_prev":50150000.0,"status":"same","is_cash":false,"share_changed":false},{"stock_code":"006340","stock_name":"대원전선","weight":5.38,"weight_prev":5.34,"weight_delta":0.04,"shares":3964.0,"shares_prev":3964.0,"shares_delta":0.0,"amount":46933760.0,"amount_prev":48479720.0,"status":"same","is_cash":false,"share_changed":false},{"stock_code":"336260","stock_name":"두산퓨얼셀","weight":5.38,"weight_prev":6.0,"weight_delta":-0.62,"shares":1222.0,"shares_prev":1222.0,"shares_delta":0.0,"amount":46924800.0,"amount_prev":54440100.0,"status":"same","is_cash":false,"share_changed":false},{"stock_code":"KRD010010001","stock_name":"현금성자산","weight":0.82,"weight_prev":-1.21,"weight_delta":2.03,"shares":7132963.0,"shares_prev":-10961127.0,"shares_delta":18094090.0,"amount":7132963.0,"amount_prev":-10961127.0,"status":"same","is_cash":true,"share_changed":false}],"summary":{"n_share_changed":3,"n_new":0,"n_removed":0,"n_rebalanced":3,"share_turnover":2.175,"is_rebalanced":true,"top_changes":[{"name":"가온전선","shares_delta":-55.0,"status":"same","weight":10.22,"weight_prev":11.85},{"name":"LS ELECTRIC","shares_delta":-27.0,"status":"same","weight":7.22,"weight_prev":7.53},{"name":"HD현대일렉트릭","shares_delta":-5.0,"status":"same","weight":7.32,"weight_prev":7.64}],"new_names":[],"removed_names":[],"turnover":3.465,"max_abs_delta":2.03},"info":{"index_name":"KRX-Akros AI 전력인프라 지수","index_desc":null,"listing":"2025.09.23","cu":"50,000","aum":"5,439억원","fee":"0.2","method":"기초지수 구성종목을 지수 비중대로 복제하는 패시브(인덱스) ETF"}}